<DOMSymbolItem xmlns:xsi="http://www.w3.org/2001/XMLSchema-instance" xmlns="http://ns.adobe.com/xfl/2008/" name="FunctionKeys/F8" itemID="5014910e-00000b42" symbolType="graphic" lastModified="1343525146">
  <timeline>
    <DOMTimeline name="F8">
      <layers>
        <DOMLayer name="Layer 1" color="#4FFF4F" current="true" isSelected="true">
          <frames>
            <DOMFrame index="0" keyMode="9728">
              <elements>
                <DOMShape>
                  <fills>
                    <FillStyle index="1">
                      <SolidColor color="#CCCCCC"/>
                    </FillStyle>
                  </fills>
                  <edges>
                    <Edge fillStyle0="1" edges="!216 85[218 74 218 62!218 62[218 42 213 28!213 28[208 14 196 7!196 7[184 0 163 0!163 0[143 0 132 8!132 8[120 16 116 30!116 30[111 45 112 62!112 62[111 74 114 85!114 85[116 97 122 106!122 106[128 115 140 120!140 120[125 124 119 135!119
 135[112 146 111 160!111 160[109 174 110 187!110 187[109 206 114 223!114 223[118 240 130 251!130 251[142 262 165 262!165 262[189 262 201 250!201 250[213 239 217 220!217 220[221 202 221 182!221 182[221 170 219 157!219 157[217 144 210 134
!210 134[204 124 190 120!190 120[202 116 208 106!208 106[214 97 216 85!183 51[184 59 184 66!184 66[184 72 182 81!182 81[181 90 177 97!177 97[173 105 165 105!165 105[157 105 152 97!152 97[148 90 147 81!147 81[146 72 146 66!146 66[146 59
 147 51!147 51[148 43 152 37!152 37[156 30 165 30!165 30[173 30 177 37!177 37[181 43 183 51!34 32|92 32!92 32|92 3!92 3|0 3!0 3|0 259!0 259|34 259!34 259|34 142!34 142|86 142!86 142|86 113!86 113|34 113!34 113|34 32!165 138[173 138 177
 144!177 144[182 150 183 158!183 158[185 166 186 174!186 174[186 183 186 189!186 189[186 196 185 206!185 206[184 216 179 224!179 224[175 231 165 232!165 232[155 231 151 224!151 224[146 216 145 206!145 206[144 196 144 189!144 189[144 183
 144 174!144 174[145 166 146 158!146 158[148 150 152 144!152 144[157 138 165 138"/>
                  </edges>
                </DOMShape>
              </elements>
            </DOMFrame>
          </frames>
        </DOMLayer>
      </layers>
    </DOMTimeline>
  </timeline>
</DOMSymbolItem>