<DOMSymbolItem xmlns:xsi="http://www.w3.org/2001/XMLSchema-instance" xmlns="http://ns.adobe.com/xfl/2008/" name="FunctionKeys/PgUp" itemID="50148c62-00000705" symbolType="graphic" lastModified="1343523938">
  <timeline>
    <DOMTimeline name="PgUp">
      <layers>
        <DOMLayer name="Layer 1" color="#4FFF4F" current="true" isSelected="true">
          <frames>
            <DOMFrame index="0" keyMode="9728">
              <elements>
                <DOMShape>
                  <fills>
                    <FillStyle index="1">
                      <SolidColor color="#CCCCCC"/>
                    </FillStyle>
                  </fills>
                  <edges>
                    <Edge fillStyle0="1" edges="!447 84|415 84!415 84|415 326!415 326|447 326!447 326|447 237!447 237[452 247 459 253!459 253[466 259 478 259!478 259[493 258 501 249!501 249[510 240 514 226!514 226[518 212 519 198!519 198[520 183 519 172!519 172[520 161 519 146!519
 146[518 131 514 116!514 116[510 102 502 92!502 92[494 82 479 82!479 82[466 82 459 88!459 88[452 95 447 106!447 106|447 84!466 110[474 111 479 118!479 118[484 125 485 135!485 135[487 145 487 155!487 155[487 165 487 170!487 170[487 185
 486 199!486 199[485 212 480 221!480 221[476 230 466 230!466 230[458 230 453 223!453 223[449 216 448 206!448 206[446 195 446 185!446 185[445 176 446 170!446 170[445 165 446 155!446 155[446 145 448 135!448 135[449 125 453 118!453 118[458
 111 466 110!345 0|345 191!345 191[345 202 344 210!344 210[342 218 337 223!337 223[331 227 320 227!320 227[313 228 307 224!307 224[302 221 299 213!299 213[296 204 296 188!296 188|296 0!296 0|262 0!262 0|262 176!262 176[261 200 265 218
!265 218[269 237 281 248!281 248[294 259 321 259!321 259[343 259 355 252!355 252[367 245 372 233!372 233[377 221 379 208!379 208[380 194 379 182!379 182|379 0!379 0|345 0!186 118[190 125 192 135!192 135[194 146 194 156!194 156[195 166
 194 171!194 171[195 176 195 186!195 186[195 196 193 206!193 206[192 216 188 223!188 223[183 230 175 230!175 230[166 230 161 223!161 223[157 215 155 205!155 205[154 194 154 184!154 184[153 174 154 169!154 169[153 164 154 155!154 155[154
 145 155 135!155 135[157 125 161 118!161 118[165 110 174 110!174 110[181 110 186 118!194 104|193 105!193 105[189 94 182 88!182 88[174 82 162 82!162 82[147 82 138 92!138 92[129 101 126 116!126 116[122 131 121 146!121 146[121 161 121 171
!121 171[121 183 122 197!122 197[123 212 126 226!126 226[130 240 139 249!139 249[148 258 163 259!163 259[174 259 182 253!182 253[190 246 193 236!193 236|194 236!194 236|194 264!194 264[194 272 194 281!194 281[193 289 189 295!189 295[185
 300 175 301!175 301[167 300 162 297!162 297[157 293 156 287!156 287[154 281 154 275!154 275|123 275!123 275|123 280!123 280[124 304 137 316!137 316[151 329 174 329!174 329[191 330 203 324!203 324[214 319 220 303!220 303[226 288 226 257
!226 257|226 84!226 84|194 84!194 84|194 104!63 1[52 0 41 0!41 0|0 0!0 0|0 256!0 256|34 256!34 256|34 142!34 142[73 144 90 126!90 126[107 107 107 68!107 68[107 44 101 30!101 30[95 16 85 9!85 9[75 3 63 1!68 50[71 59 71 71!71 71[71 93 63
 104!63 104[55 115 34 114!34 114|34 29!34 29|39 29!39 29[51 29 59 34!59 34[66 40 68 50"/>
                  </edges>
                </DOMShape>
              </elements>
            </DOMFrame>
          </frames>
        </DOMLayer>
      </layers>
    </DOMTimeline>
  </timeline>
</DOMSymbolItem>