<DOMSymbolItem xmlns:xsi="http://www.w3.org/2001/XMLSchema-instance" xmlns="http://ns.adobe.com/xfl/2008/" name="Named Icons/Symbol 459" itemID="5b986e27-00000a01" linkageExportForAS="true" linkageIdentifier="PS3_START" lastModified="1535509198">
  <timeline>
    <DOMTimeline name="Symbol 459">
      <layers>
        <DOMLayer name="Layer 1" color="#D6328C">
          <frames>
            <DOMFrame index="0" keyMode="9728">
              <elements>
                <DOMSymbolInstance libraryItemName="Named Icons/Symbol 458" symbolType="graphic" loop="loop">
                  <transformationPoint>
                    <Point/>
                  </transformationPoint>
                </DOMSymbolInstance>
              </elements>
            </DOMFrame>
          </frames>
        </DOMLayer>
        <DOMLayer name="Layer 2" color="#F1C982" current="true" isSelected="true">
          <frames>
            <DOMFrame index="0" keyMode="9728">
              <elements>
                <DOMSymbolInstance libraryItemName="Named Icons/Symbol 457" centerPoint3DX="30.5" centerPoint3DY="13">
                  <matrix>
                    <Matrix tx="-1.3"/>
                  </matrix>
                  <transformationPoint>
                    <Point/>
                  </transformationPoint>
                  <color>
                    <Color alphaMultiplier="0.6015625"/>
                  </color>
                </DOMSymbolInstance>
              </elements>
            </DOMFrame>
          </frames>
        </DOMLayer>
      </layers>
    </DOMTimeline>
  </timeline>
</DOMSymbolItem>