<DOMSymbolItem xmlns:xsi="http://www.w3.org/2001/XMLSchema-instance" xmlns="http://ns.adobe.com/xfl/2008/" name="Named Icons/Symbol 290" itemID="5b986e27-00000966" lastModified="1535509198">
  <timeline>
    <DOMTimeline name="Symbol 290">
      <layers>
        <DOMLayer name="Layer 1" color="#DB5497" current="true" isSelected="true">
          <frames>
            <DOMFrame index="0" keyMode="9728">
              <elements>
                <DOMSymbolInstance libraryItemName="Named Icons/Symbol 289" symbolType="graphic" loop="loop">
                  <transformationPoint>
                    <Point/>
                  </transformationPoint>
                </DOMSymbolInstance>
              </elements>
            </DOMFrame>
          </frames>
        </DOMLayer>
      </layers>
    </DOMTimeline>
  </timeline>
</DOMSymbolItem>