<DOMSymbolItem xmlns:xsi="http://www.w3.org/2001/XMLSchema-instance" xmlns="http://ns.adobe.com/xfl/2008/" name="Symbols/Negation" itemID="50146e33-00000315" symbolType="graphic" lastModified="1343521875">
  <timeline>
    <DOMTimeline name="Negation">
      <layers>
        <DOMLayer name="Layer 1" color="#4FFF4F" current="true" isSelected="true">
          <frames>
            <DOMFrame index="0" keyMode="9728">
              <elements>
                <DOMShape selected="true" isFloating="true">
                  <matrix>
                    <Matrix a="0.604721069335938" d="0.602935791015625" tx="-1.55" ty="-4.6"/>
                  </matrix>
                  <fills>
                    <FillStyle index="1">
                      <SolidColor color="#CCCCCC"/>
                    </FillStyle>
                  </fills>
                  <edges>
                    <Edge fillStyle0="1" edges="!169 242S1|192 242!192 242|192 152!192 152|52 152!52 152|52 175!52 175|169 175!169 175|169 242"/>
                  </edges>
                </DOMShape>
              </elements>
            </DOMFrame>
          </frames>
        </DOMLayer>
      </layers>
    </DOMTimeline>
  </timeline>
</DOMSymbolItem>