<DOMSymbolItem xmlns:xsi="http://www.w3.org/2001/XMLSchema-instance" xmlns="http://ns.adobe.com/xfl/2008/" name="Letters/A" itemID="50146f2d-00000325" symbolType="graphic" lastModified="1343521495">
  <timeline>
    <DOMTimeline name="A">
      <layers>
        <DOMLayer name="Layer 1" color="#4FFF4F" current="true" isSelected="true">
          <frames>
            <DOMFrame index="0" keyMode="9728">
              <elements>
                <DOMShape>
                  <fills>
                    <FillStyle index="1">
                      <SolidColor color="#CCCCCC"/>
                    </FillStyle>
                  </fills>
                  <edges>
                    <Edge fillStyle0="1" edges="!56 0S1|0 256!0 256|34 256!34 256|43 206!43 206|94 206!94 206|104 256!104 256|138 256!138 256|83 0!83 0|56 0!48 179|69 49!69 49|89 179!89 179|48 179"/>
                  </edges>
                </DOMShape>
              </elements>
            </DOMFrame>
          </frames>
        </DOMLayer>
      </layers>
    </DOMTimeline>
  </timeline>
</DOMSymbolItem>