<DOMSymbolItem xmlns:xsi="http://www.w3.org/2001/XMLSchema-instance" xmlns="http://ns.adobe.com/xfl/2008/" name="Letters/Z" itemID="50146fe9-00000357" symbolType="graphic" lastModified="1343521672">
  <timeline>
    <DOMTimeline name="Z">
      <layers>
        <DOMLayer name="Layer 1" color="#4FFF4F" current="true" isSelected="true">
          <frames>
            <DOMFrame index="0" keyMode="9728">
              <elements>
                <DOMShape>
                  <fills>
                    <FillStyle index="1">
                      <SolidColor color="#CCCCCC"/>
                    </FillStyle>
                  </fills>
                  <edges>
                    <Edge fillStyle0="1" edges="!9 29|78 29!78 29|0 256!0 256|118 256!118 256|118 226!118 226|45 226!45 226|123 0!123 0|9 0!9 0|9 29"/>
                  </edges>
                </DOMShape>
              </elements>
            </DOMFrame>
          </frames>
        </DOMLayer>
      </layers>
    </DOMTimeline>
  </timeline>
</DOMSymbolItem>